unittrial/__init__.py
unittrial/assertions.py
unittrial/console.py
unittrial/logger.py
unittrial/testcase.py
unittrial/testconfig.py
unittrial-0.2.3.dist-info/LICENSE
unittrial-0.2.3.dist-info/METADATA
unittrial-0.2.3.dist-info/WHEEL
unittrial-0.2.3.dist-info/top_level.txt
unittrial-0.2.3.dist-info/RECORD
