Metadata-Version: 2.1
Name: unittrial
Version: 0.2.3
Summary: Python Test Framework
Home-page: https://github.com/TeddyBearSuicide/unittrial
Author: TeddyBearSuicide
Author-email: UNKNOWN
License: UNKNOWN
Platform: UNKNOWN
Classifier: Programming Language :: Python :: 3
Classifier: License :: OSI Approved :: GNU Lesser General Public License v2 or later (LGPLv2+)
Classifier: Operating System :: OS Independent
